bitso/__init__.py
bitso/api.py
bitso/bitsows.py
bitso/errors.py
bitso/models.py
bitso_py-3.0.1.dist-info/METADATA
bitso_py-3.0.1.dist-info/RECORD
bitso_py-3.0.1.dist-info/WHEEL
bitso_py-3.0.1.dist-info/top_level.txt
tests/__init__.py
tests/test_api.py
