Metadata-Version: 2.1
Name: bitso-py
Version: 3.0.1
Summary: A python wrapper for the Bitso API.
Home-page: https://github.com/bitsoex/bitso-py
Author: Mario Romero
Author-email: mario@bitso.com
License: LICENSE.txt
Platform: UNKNOWN
Requires-Dist: requests (>=2.2.1)
Requires-Dist: websocket-client (==0.40.0)
Requires-Dist: python-dateutil (>=1.5)
Requires-Dist: mock (>=2.0.0)
Requires-Dist: future (>=0.16.0)
